scdatatools/__init__.py
scdatatools/__main__.py
scdatatools/actionmap.py
scdatatools/p4k.py
scdatatools/profile.py
scdatatools/utils.py
scdatatools/blender/__init__.py
scdatatools/blender/logging.py
scdatatools/blender/addon/__init__.py
scdatatools/blender/addon/header_menu.py
scdatatools/blender/addon/preferences.py
scdatatools/blender/addon/utils.py
scdatatools/blender/blueprints/__init__.py
scdatatools/blender/blueprints/hooks.py
scdatatools/blender/blueprints/lighting.py
scdatatools/blender/blueprints/manager.py
scdatatools/blender/blueprints/ui.py
scdatatools/blender/blueprints/utilities.py
scdatatools/blender/materials/SCShaders.blend
scdatatools/blender/materials/__init__.py
scdatatools/blender/materials/utils.py
scdatatools/blender/utils/__init__.py
scdatatools/blender/utils/ui_utils.py
scdatatools/blender/utils/validation.py
scdatatools/cli/__init__.py
scdatatools/cli/__main__.py
scdatatools/cli/commands/__init__.py
scdatatools/cli/commands/blender.py
scdatatools/cli/commands/cryxml.py
scdatatools/cli/commands/forge.py
scdatatools/cli/commands/inventory.py
scdatatools/cli/commands/p4k.py
scdatatools/cli/commands/profile.py
scdatatools/cli/commands/texture.py
scdatatools/engine/__init__.py
scdatatools/engine/model_utils.py
scdatatools/engine/utils.py
scdatatools/engine/chunkfile/__init__.py
scdatatools/engine/chunkfile/asset_extractor.py
scdatatools/engine/chunkfile/chcr.py
scdatatools/engine/chunkfile/converter.py
scdatatools/engine/chunkfile/ivo.py
scdatatools/engine/chunkfile/chunks/__init__.py
scdatatools/engine/chunkfile/chunks/base.py
scdatatools/engine/chunkfile/chunks/data.py
scdatatools/engine/chunkfile/chunks/defs.py
scdatatools/engine/chunkfile/chunks/unknown.py
scdatatools/engine/chunkfile/chunks/geometry/__init__.py
scdatatools/engine/chunkfile/chunks/geometry/materials.py
scdatatools/engine/chunkfile/chunks/geometry/nodes.py
scdatatools/engine/chunkfile/chunks/soc/__init__.py
scdatatools/engine/chunkfile/chunks/soc/area_shape.py
scdatatools-1.0.3.dist-info/AUTHORS.rst
scdatatools-1.0.3.dist-info/LICENSE
scdatatools-1.0.3.dist-info/METADATA
scdatatools-1.0.3.dist-info/WHEEL
scdatatools-1.0.3.dist-info/entry_points.txt
scdatatools-1.0.3.dist-info/top_level.txt
scdatatools-1.0.3.dist-info/zip-safe
scdatatools-1.0.3.dist-info/RECORD
