Metadata-Version: 2.1
Name: scdatatools
Version: 1.0.3
Summary: Python tools for working with Star Citizen data files.
Home-page: https://gitlab.com/scmodding/frameworks/scdatatools
Author: ventorvar
Author-email: ventorvar@gmail.com
License: MIT license
Keywords: scdatatools
Platform: UNKNOWN
Classifier: Development Status :: 2 - Pre-Alpha
Classifier: Intended Audience :: Developers
Classifier: License :: OSI Approved :: MIT License
Classifier: Natural Language :: English
Classifier: Programming Language :: Python :: 3
Classifier: Programming Language :: Python :: 3.8
License-File: LICENSE
License-File: AUTHORS.rst
Requires-Dist: fnvhash (~=0.1.0)
Requires-Dist: hexdump (~=3.3)
Requires-Dist: humanize (~=3.13.1)
Requires-Dist: numpy (~=1.21.5)
Requires-Dist: pycryptodome (~=3.12.0)
Requires-Dist: pyquaternion (~=0.9.9)
Requires-Dist: pyrsi (~=0.1.19)
Requires-Dist: python-nubia (~=0.2b2)
Requires-Dist: sentry-sdk (==1.5.8)
Requires-Dist: tqdm (~=4.62.3)
Requires-Dist: xxhash (~=2.0.2)
Requires-Dist: zstandard (~=0.12.0)
